python_retry/__init__.py
python_retry/retry.py
python_retry-0.0.1.dist-info/LICENSE
python_retry-0.0.1.dist-info/METADATA
python_retry-0.0.1.dist-info/WHEEL
python_retry-0.0.1.dist-info/entry_points.txt
python_retry-0.0.1.dist-info/top_level.txt
python_retry-0.0.1.dist-info/RECORD
