Metadata-Version: 2.1
Name: python-retry
Version: 0.0.1
Summary: Retry package for Python
Home-page: https://github.com/pyprogrammerblog/python-retry
Author: JM Vazquez
Author-email: 
License: MIT License
Keywords: python,retry
Platform: UNKNOWN
Classifier: Programming Language :: Python :: 3
Classifier: License :: OSI Approved :: MIT License
Classifier: Operating System :: OS Independent
Requires-Python: >=3.6
License-File: LICENSE
Provides-Extra: test
Requires-Dist: pytest ; extra == 'test'
